edges_estimate/__init__.py
edges_estimate/calibration.py
edges_estimate/eor_models.py
edges_estimate/fitting.py
edges_estimate/foregrounds.py
edges_estimate/likelihoods.py
edges_estimate/plots.py
edges_estimate-1.3.0.dist-info/LICENSE
edges_estimate-1.3.0.dist-info/METADATA
edges_estimate-1.3.0.dist-info/WHEEL
edges_estimate-1.3.0.dist-info/top_level.txt
edges_estimate-1.3.0.dist-info/RECORD
