Metadata-Version: 2.1
Name: edges-estimate
Version: 1.3.0
Summary: Parameter Estimation for EDGES
Home-page: https://github.com/edges-collab/edges-estimate
Author: EDGES Team
License: mit
Platform: any
Classifier: Development Status :: 4 - Beta
Classifier: Intended Audience :: Developers
Classifier: Natural Language :: English
Classifier: Programming Language :: Python
Classifier: Programming Language :: Python :: 2
Classifier: Programming Language :: Python :: 2.7
Classifier: Programming Language :: Python :: 3
Classifier: Programming Language :: Python :: 3.8
Classifier: Programming Language :: Python :: 3.9
Classifier: Programming Language :: Python :: 3.10
Classifier: Programming Language :: Python :: Implementation :: CPython
Requires-Python: !=3.0.*,!=3.1.*,!=3.2.*,!=3.3.*,!=3.4.*,!=3.5.*,!=3.6.*,!=3.7.*,>=2.7
License-File: LICENSE
Requires-Dist: cached-property
Requires-Dist: click (>=6.0)
Requires-Dist: edges-cal
Requires-Dist: numpy
Requires-Dist: scipy
Requires-Dist: yabf (>=2.0)
Provides-Extra: dev
Requires-Dist: edges-analysis ; extra == 'dev'
Requires-Dist: ipython ; extra == 'dev'
Requires-Dist: nbsphinx ; extra == 'dev'
Requires-Dist: numdifftools ; extra == 'dev'
Requires-Dist: pre-commit ; extra == 'dev'
Requires-Dist: pytest ; extra == 'dev'
Requires-Dist: pytest-cases ; extra == 'dev'
Requires-Dist: pytest-cov ; extra == 'dev'
Requires-Dist: pytest-plt ; extra == 'dev'
Requires-Dist: sphinx ; extra == 'dev'
Requires-Dist: sphinx-rtd-theme ; extra == 'dev'
Provides-Extra: docs
Requires-Dist: ipython ; extra == 'docs'
Requires-Dist: nbsphinx ; extra == 'docs'
Requires-Dist: sphinx ; extra == 'docs'
Requires-Dist: sphinx-rtd-theme ; extra == 'docs'
Provides-Extra: test
Requires-Dist: edges-analysis ; extra == 'test'
Requires-Dist: numdifftools ; extra == 'test'
Requires-Dist: pre-commit ; extra == 'test'
Requires-Dist: pytest ; extra == 'test'
Requires-Dist: pytest-cases ; extra == 'test'
Requires-Dist: pytest-cov ; extra == 'test'
Requires-Dist: pytest-plt ; extra == 'test'
